sandfs/__init__.py
sandfs/adapters.py
sandfs/exceptions.py
sandfs/hooks.py
sandfs/integrations.py
sandfs/nodes.py
sandfs/policies.py
sandfs/providers.py
sandfs/pyexec.py
sandfs/shell.py
sandfs/vfs.py
sandfs-0.2.2.dist-info/METADATA
sandfs-0.2.2.dist-info/WHEEL
sandfs-0.2.2.dist-info/licenses/LICENSE
sandfs-0.2.2.dist-info/RECORD
