Metadata-Version: 2.4
Name: sandfs
Version: 0.2.2
Summary: Composable virtual filesystem sandbox with a UNIX-like command surface for agents
Project-URL: Homepage, https://example.com/sandfs
Project-URL: Repository, https://example.com/sandfs.git
Author: sandfs contributors
License: MIT
License-File: LICENSE
Keywords: agents,in-memory,sandbox,virtual filesystem
Classifier: Development Status :: 3 - Alpha
Classifier: License :: OSI Approved :: MIT License
Classifier: Programming Language :: Python :: 3
Classifier: Topic :: Software Development :: Libraries
Classifier: Topic :: System :: Filesystems
Requires-Python: >=3.10
Provides-Extra: dev
Requires-Dist: pytest>=7.0; extra == 'dev'
